[
  {
    "id": "62001001",
    "b": 62,
    "c": 1,
    "v": 1,
    "t": "Das Wort, das zum Leben führt, war von Anfang an da. Wir haben es selbst gehört und mit eigenen Augen gesehen, ja, wir haben es angeschaut und sogar mit unseren Händen berührt.",
    "h": "Leben in Gemeinschaft mit dem Vater und dem Sohn\n(Kapitel 1–3)\nDas Wort, das zum Leben führt",
    "o": 1,
    "l": "1"
  },
  {
    "id": "62001002",
    "b": 62,
    "c": 1,
    "v": 2,
    "t": "Dieses Leben ist offenbar geworden. Wir haben es gesehen und können es bezeugen. Deshalb verkünden wir die Botschaft vom ewigen Leben. Es war bei Gott, dem Vater, und hat sich uns gezeigt.",
    "h": "",
    "o": 2,
    "l": "2"
  },
  {
    "id": "62001003",
    "b": 62,
    "c": 1,
    "v": 3,
    "t": "Was wir nun selbst gesehen und gehört haben, das geben wir euch weiter, damit auch ihr mit uns im Glauben verbunden seid. So haben wir Gemeinschaft miteinander und zugleich mit Gott, dem Vater, und mit seinem Sohn Jesus Christus.",
    "h": "",
    "o": 3,
    "l": "3"
  },
  {
    "id": "62001004",
    "b": 62,
    "c": 1,
    "v": 4,
    "t": "Wir schreiben euch das, damit wir uns von ganzem Herzen freuen können.",
    "h": "",
    "o": 4,
    "l": "4"
  },
  {
    "id": "62001005",
    "b": 62,
    "c": 1,
    "v": 5,
    "t": "Das ist die Botschaft, die wir von Christus gehört haben und die wir euch weitersagen: Gott ist Licht. In ihm gibt es keine Finsternis.",
    "h": "Leben im Licht Gottes",
    "o": 5,
    "l": "5"
  },
  {
    "id": "62001006",
    "b": 62,
    "c": 1,
    "v": 6,
    "t": "Wenn wir also behaupten, dass wir zu Gott gehören, und dennoch in der Finsternis leben, dann lügen wir und widersprechen mit unserem Leben der Wahrheit.",
    "h": "",
    "o": 6,
    "l": "6"
  },
  {
    "id": "62001007",
    "b": 62,
    "c": 1,
    "v": 7,
    "t": "Leben wir aber im Licht, so wie Gott im Licht ist, dann haben wir Gemeinschaft miteinander. Und das Blut, das sein Sohn Jesus Christus für uns vergossen hat, befreit uns von aller Schuld.",
    "h": "",
    "o": 7,
    "l": "7"
  },
  {
    "id": "62001008",
    "b": 62,
    "c": 1,
    "v": 8,
    "t": "Wenn wir behaupten, sündlos zu sein, betrügen wir uns selbst. Dann lebt die Wahrheit nicht in uns.",
    "h": "",
    "o": 8,
    "l": "8"
  },
  {
    "id": "62001009",
    "b": 62,
    "c": 1,
    "v": 9,
    "t": "Wenn wir aber unsere Sünden bekennen, dann erweist sich Gott als treu und gerecht: Er wird unsere Sünden vergeben und uns von allem Bösen reinigen.",
    "h": "",
    "o": 9,
    "l": "9"
  },
  {
    "id": "62001010",
    "b": 62,
    "c": 1,
    "v": 10,
    "t": "Doch wenn wir behaupten, wir hätten gar nicht gesündigt, dann machen wir Gott zum Lügner und zeigen damit nur, dass seine Botschaft in uns keinen Raum hat.",
    "h": "",
    "o": 10,
    "l": "10"
  },
  {
    "id": "62002001",
    "b": 62,
    "c": 2,
    "v": 1,
    "t": "Meine geliebten Kinder, ich schreibe euch dies, damit ihr nicht sündigt. Sollte aber doch jemand Schuld auf sich laden, dann tritt einer beim Vater für uns ein, der selbst ohne jede Sünde ist: Jesus Christus.",
    "h": "Woran man einen Christen erkennt",
    "o": 1,
    "l": "1"
  },
  {
    "id": "62002002",
    "b": 62,
    "c": 2,
    "v": 2,
    "t": "Denn Christus hat unsere Sünden, ja, die Sünden der ganzen Welt auf sich genommen; er hat sie gesühnt.",
    "h": "",
    "o": 2,
    "l": "2"
  },
  {
    "id": "62002003",
    "b": 62,
    "c": 2,
    "v": 3,
    "t": "Wenn wir uns an Gottes Gebote halten, zeigt uns dies, dass wir Gott kennen.",
    "h": "",
    "o": 3,
    "l": "3"
  },
  {
    "id": "62002004",
    "b": 62,
    "c": 2,
    "v": 4,
    "t": "Wenn jemand behauptet: »Ich kenne Gott«, hält sich aber nicht an seine Gebote, so ist er ein Lügner; die Wahrheit lebt nicht in ihm.",
    "h": "",
    "o": 4,
    "l": "4"
  },
  {
    "id": "62002005",
    "b": 62,
    "c": 2,
    "v": 5,
    "t": "Doch wer sich nach dem richtet, was Gott gesagt hat, bei dem ist Gottes Liebe zum Ziel gekommen. Daran erkennen wir, ob wir wirklich mit ihm verbunden sind.",
    "h": "",
    "o": 5,
    "l": "5"
  },
  {
    "id": "62002006",
    "b": 62,
    "c": 2,
    "v": 6,
    "t": "Wer von sich sagt, dass er zu ihm gehört, der soll auch so leben, wie Jesus gelebt hat.",
    "h": "",
    "o": 6,
    "l": "6"
  },
  {
    "id": "62002007",
    "b": 62,
    "c": 2,
    "v": 7,
    "t": "Was ich euch jetzt schreibe, meine Lieben, ist kein neues Gebot, sondern die Botschaft Gottes, die ihr von Anfang an gehört habt.",
    "h": "Das alte und das neue Gebot",
    "o": 7,
    "l": "7"
  },
  {
    "id": "62002008",
    "b": 62,
    "c": 2,
    "v": 8,
    "t": "Und trotzdem ist dieses Gebot neu, weil Christus es verwirklicht hat und ihr jetzt danach lebt. Denn die Finsternis schwindet, und das wahre Licht strahlt schon auf.",
    "h": "",
    "o": 8,
    "l": "8"
  },
  {
    "id": "62002009",
    "b": 62,
    "c": 2,
    "v": 9,
    "t": "Wenn nun jemand behauptet, in diesem Licht zu leben, hasst aber seinen Bruder oder seine Schwester, dann lebt er in Wirklichkeit immer noch in der Finsternis.",
    "h": "",
    "o": 9,
    "l": "9"
  },
  {
    "id": "62002010",
    "b": 62,
    "c": 2,
    "v": 10,
    "t": "Nur wer seine Geschwister liebt, der lebt wirklich im Licht. An ihm lässt sich nichts Anstößiges finden.",
    "h": "",
    "o": 10,
    "l": "10"
  },
  {
    "id": "62002011",
    "b": 62,
    "c": 2,
    "v": 11,
    "t": "Wer dagegen seinen Bruder oder seine Schwester hasst, der lebt ganz und gar in der Finsternis und weiß nicht, wohin er geht. Er ist wie ein Blinder und kann nichts sehen, weil die Dunkelheit ihn umgibt.",
    "h": "",
    "o": 11,
    "l": "11"
  },
  {
    "id": "62002012",
    "b": 62,
    "c": 2,
    "v": 12,
    "t": "Dies schreibe ich euch, meine geliebten Kinder, weil ich weiß, dass eure Sünden durch Jesus Christus vergeben sind.",
    "h": "",
    "o": 12,
    "l": "12"
  },
  {
    "id": "62002013",
    "b": 62,
    "c": 2,
    "v": 13,
    "t": "Euch Vätern schreibe ich, weil ihr den kennt, der von Anfang an da war. Ich wende mich aber auch an euch, ihr jungen Leute; denn ihr habt den Teufel besiegt.",
    "h": "",
    "o": 13,
    "l": "13"
  },
  {
    "id": "62002014",
    "b": 62,
    "c": 2,
    "v": 14,
    "t": "Ich will es noch einmal sagen: Euch Kindern schreibe ich, weil ihr den Vater kennt; ebenso wende ich mich an euch Väter, weil ihr den kennt, der von Anfang an da war. Und euch, ihr jungen Leute, schreibe ich, weil ihr im Glauben stark geworden seid. Gottes Wort wohnt in euch, und ihr habt den Teufel besiegt.",
    "h": "",
    "o": 14,
    "l": "14"
  },
  {
    "id": "62002015",
    "b": 62,
    "c": 2,
    "v": 15,
    "t": "Liebt nicht diese Welt und hängt euer Herz nicht an irgendetwas, das zu dieser Welt gehört. Denn wer die Welt liebt, kann nicht zugleich Gott, den Vater, lieben.",
    "h": "",
    "o": 15,
    "l": "15"
  },
  {
    "id": "62002016",
    "b": 62,
    "c": 2,
    "v": 16,
    "t": "Was gehört nun zum Wesen dieser Welt? Selbstsüchtige Wünsche, die Gier nach allem, was einem ins Auge fällt, das Prahlen mit Wohlstand und Macht. All dies kommt nicht von Gott, unserem Vater, sondern gehört zur Welt.",
    "h": "",
    "o": 16,
    "l": "16"
  },
  {
    "id": "62002017",
    "b": 62,
    "c": 2,
    "v": 17,
    "t": "Die Welt aber mit ihrer Unersättlichkeit wird vergehen. Nur wer tut, was Gott will, wird ewig leben.",
    "h": "",
    "o": 17,
    "l": "17"
  },
  {
    "id": "62002018",
    "b": 62,
    "c": 2,
    "v": 18,
    "t": "Das Ende dieser Welt ist nahe, meine geliebten Kinder! Ihre letzte Stunde ist angebrochen. Ihr wisst, dass zu dieser Zeit der Feind von Christus, der Antichrist, kommen wird. Schon jetzt sind viele Antichristen aufgetreten. Daran können wir erkennen, dass die Welt ihrem Ende entgegengeht.",
    "h": "Nichts soll euch von Christus trennen",
    "o": 18,
    "l": "18"
  },
  {
    "id": "62002019",
    "b": 62,
    "c": 2,
    "v": 19,
    "t": "Diese Feinde von Christus kommen zwar aus unseren eigenen Reihen, in Wirklichkeit aber haben sie nie zu uns gehört. Sonst hätten sie sich nicht von uns getrennt. Nun aber ist für jedermann sichtbar geworden, dass sie gar nicht zu uns gehören.",
    "h": "",
    "o": 19,
    "l": "19"
  },
  {
    "id": "62002020",
    "b": 62,
    "c": 2,
    "v": 20,
    "t": "Doch euch hat Christus seinen Heiligen Geist gegeben, und deshalb kennt ihr alle die Wahrheit.",
    "h": "",
    "o": 20,
    "l": "20"
  },
  {
    "id": "62002021",
    "b": 62,
    "c": 2,
    "v": 21,
    "t": "Ich schreibe euch also nicht, weil ich meinte, ihr müsstet die Wahrheit erst noch erfahren. Ihr kennt sie sehr gut und wisst auch, dass aus ihr keinerlei Lüge kommen kann.",
    "h": "",
    "o": 21,
    "l": "21"
  },
  {
    "id": "62002022",
    "b": 62,
    "c": 2,
    "v": 22,
    "t": "Wenn nun jemand behauptet, Jesus sei gar nicht der Christus, der von Gott gesandte Retter, muss dieser Mensch nicht der Lügner schlechthin sein? Wer den Vater und den Sohn leugnet, ist ohne jeden Zweifel ein Antichrist.",
    "h": "",
    "o": 22,
    "l": "22"
  },
  {
    "id": "62002023",
    "b": 62,
    "c": 2,
    "v": 23,
    "t": "Denn wer den Sohn ablehnt, der ist auch nicht mit dem Vater verbunden. Doch wer sich zum Sohn bekennt, der hat auch Gemeinschaft mit dem Vater.",
    "h": "",
    "o": 23,
    "l": "23"
  },
  {
    "id": "62002024",
    "b": 62,
    "c": 2,
    "v": 24,
    "t": "Lasst euch also nicht von der Botschaft abbringen, die ihr von Anfang an gehört habt. Wenn sie in euren Herzen bleibt, dann werdet ihr für immer mit Gott, dem Vater, und mit seinem Sohn Jesus Christus verbunden sein.",
    "h": "",
    "o": 24,
    "l": "24"
  },
  {
    "id": "62002025",
    "b": 62,
    "c": 2,
    "v": 25,
    "t": "Denn genau das hat Christus uns zugesagt: ewiges Leben in der Verbindung mit ihm.",
    "h": "",
    "o": 25,
    "l": "25"
  },
  {
    "id": "62002026",
    "b": 62,
    "c": 2,
    "v": 26,
    "t": "Das müsst ihr über diese Leute wissen, die euch vom richtigen Weg abbringen wollen.",
    "h": "",
    "o": 26,
    "l": "26"
  },
  {
    "id": "62002027",
    "b": 62,
    "c": 2,
    "v": 27,
    "t": "Doch der Heilige Geist, den euch Christus gegeben hat, er bleibt in euch. Deshalb braucht ihr keine anderen Lehrer, der Heilige Geist selbst ist in allen Fragen euer Lehrer. Was er euch sagt, ist wahr und ohne Lüge. Haltet also an dem fest, was euch der Geist lehrt: Bleibt mit Christus verbunden.",
    "h": "",
    "o": 27,
    "l": "27"
  },
  {
    "id": "62002028",
    "b": 62,
    "c": 2,
    "v": 28,
    "t": "Meine Kinder, lasst euch durch nichts von Christus trennen. Dann werden wir ihm voller Zuversicht entgegengehen und brauchen nicht beschämt zurückzuweichen.",
    "h": "",
    "o": 28,
    "l": "28"
  },
  {
    "id": "62002029",
    "b": 62,
    "c": 2,
    "v": 29,
    "t": "Ihr wisst, dass Christus so gelebt hat, wie es Gott gefällt. Also könnt ihr davon ausgehen, dass jeder, der ebenso lebt, zu seinen Kindern gehört.",
    "h": "",
    "o": 29,
    "l": "29"
  },
  {
    "id": "62003001",
    "b": 62,
    "c": 3,
    "v": 1,
    "t": "Seht doch, wie sehr uns der Vater geliebt hat! Seine Liebe ist so groß, dass er uns seine Kinder nennt – und wir sind es wirklich! Als seine Kinder sind wir Fremde für diese Welt, weil Gott für sie ein Fremder ist.",
    "h": "Was es bedeutet, Gottes Kind zu sein",
    "o": 1,
    "l": "1"
  },
  {
    "id": "62003002",
    "b": 62,
    "c": 3,
    "v": 2,
    "t": "Meine Lieben, wir sind also schon jetzt Kinder Gottes. Aber was das bedeutet, ist noch gar nicht in vollem Umfang sichtbar. Wir wissen jedoch: Wenn Christus kommt, werden wir ihm ähnlich sein, denn wir werden ihn sehen, wie er wirklich ist.",
    "h": "",
    "o": 2,
    "l": "2"
  },
  {
    "id": "62003003",
    "b": 62,
    "c": 3,
    "v": 3,
    "t": "Wer diese Hoffnung hat, der meidet jede Schuld, so wie Christus ohne Schuld war.",
    "h": "",
    "o": 3,
    "l": "3"
  },
  {
    "id": "62003004",
    "b": 62,
    "c": 3,
    "v": 4,
    "t": "Wer sündigt, lehnt sich gegen Gott und seine Gebote auf, denn sündigen heißt: Gottes Gebote missachten.",
    "h": "",
    "o": 4,
    "l": "4"
  },
  {
    "id": "62003005",
    "b": 62,
    "c": 3,
    "v": 5,
    "t": "Doch ihr wisst ja, dass Christus auf diese Erde kam, um die Sünden der Menschen wegzunehmen, und er selbst ist ohne jede Sünde.",
    "h": "",
    "o": 5,
    "l": "5"
  },
  {
    "id": "62003006",
    "b": 62,
    "c": 3,
    "v": 6,
    "t": "Wer mit Christus verbunden bleibt, der wird nicht länger sündigen. Wer aber weiter sündigt, der weiß nichts von Christus und kennt ihn nicht.",
    "h": "",
    "o": 6,
    "l": "6"
  },
  {
    "id": "62003007",
    "b": 62,
    "c": 3,
    "v": 7,
    "t": "Meine geliebten Kinder! Lasst euch durch niemanden vom richtigen Weg abbringen! Ihr dürft nur dem vertrauen, der wie Christus ein Leben führt, das Gott gefällt.",
    "h": "",
    "o": 7,
    "l": "7"
  },
  {
    "id": "62003008",
    "b": 62,
    "c": 3,
    "v": 8,
    "t": "Wer sich aber gegen Gott auflehnt, gehört dem Teufel. Denn der Teufel hat sich von Anfang an gegen Gott aufgelehnt. Doch der Sohn Gottes ist gerade deswegen in die Welt gekommen, um die Werke des Teufels zu zerstören.",
    "h": "",
    "o": 8,
    "l": "8"
  },
  {
    "id": "62003009",
    "b": 62,
    "c": 3,
    "v": 9,
    "t": "Wer von Gott neues Leben bekommen hat und zu seinen Kindern gehört, der sündigt nicht; denn Gott hat ihm seine Kraft geschenkt, die neues Leben in ihm schafft. Weil er ein Kind Gottes ist, kann er nicht länger als Sünder leben.",
    "h": "",
    "o": 9,
    "l": "9"
  },
  {
    "id": "62003010",
    "b": 62,
    "c": 3,
    "v": 10,
    "t": "Daran kann also jeder erkennen, wer ein Kind Gottes oder wer ein Kind des Teufels ist. Alle, die Unrecht tun und ihren Bruder oder ihre Schwester nicht lieben, sind niemals Gottes Kinder.",
    "h": "",
    "o": 10,
    "l": "10"
  },
  {
    "id": "62003011",
    "b": 62,
    "c": 3,
    "v": 11,
    "t": "Von Anfang an habt ihr diese Botschaft gehört: Wir sollen einander lieben.",
    "h": "Der Maßstab für unsere Liebe",
    "o": 11,
    "l": "11"
  },
  {
    "id": "62003012",
    "b": 62,
    "c": 3,
    "v": 12,
    "t": "Nicht Kain darf unser Vorbild sein. Er war ein Kind des Teufels und tötete seinen Bruder Abel. Und warum hat er ihn ermordet? Weil seine eigenen Taten böse waren, aber das Leben seines Bruders Gott gefiel.",
    "h": "",
    "o": 12,
    "l": "12"
  },
  {
    "id": "62003013",
    "b": 62,
    "c": 3,
    "v": 13,
    "t": "Genau aus demselben Grund hasst euch die Welt. Wundert euch also nicht darüber, liebe Brüder und Schwestern.",
    "h": "",
    "o": 13,
    "l": "13"
  },
  {
    "id": "62003014",
    "b": 62,
    "c": 3,
    "v": 14,
    "t": "Wir wissen, dass wir vom ewigen Tod gerettet wurden und jetzt neues Leben haben. Das zeigt sich an der Liebe zu unseren Brüdern und Schwestern. Wer nicht liebt, der bleibt dem Tod ausgeliefert.",
    "h": "",
    "o": 14,
    "l": "14"
  },
  {
    "id": "62003015",
    "b": 62,
    "c": 3,
    "v": 15,
    "t": "Jeder, der seinen Bruder oder seine Schwester hasst, ist ein Mörder. Und das wisst ihr: Ein Mörder hat das ewige Leben nicht in sich.",
    "h": "",
    "o": 15,
    "l": "15"
  },
  {
    "id": "62003016",
    "b": 62,
    "c": 3,
    "v": 16,
    "t": "Wie sehr Christus uns liebt, haben wir daran erkannt, dass er sein Leben für uns opferte. Ebenso müssen auch wir bereit sein, unser Leben für unsere Geschwister hinzugeben.",
    "h": "",
    "o": 16,
    "l": "16"
  },
  {
    "id": "62003017",
    "b": 62,
    "c": 3,
    "v": 17,
    "t": "Denn wie kann Gottes Liebe in einem Menschen sein, wenn dieser die Not seines Bruders vor Augen hat, sie ihm aber gleichgültig ist? Und das, obwohl er selbst alles hat, was er zum Leben braucht!",
    "h": "",
    "o": 17,
    "l": "17"
  },
  {
    "id": "62003018",
    "b": 62,
    "c": 3,
    "v": 18,
    "t": "Deshalb, meine Kinder, lasst uns einander lieben: nicht mit leeren Worten, sondern mit tatkräftiger Liebe und in aller Aufrichtigkeit.",
    "h": "Gott ist größer als unser Gewissen",
    "o": 18,
    "l": "18"
  },
  {
    "id": "62003019",
    "b": 62,
    "c": 3,
    "v": 19,
    "t": "Daran erkennen wir, dass die Wahrheit unser Leben bestimmt. So können wir mit einem guten Gewissen vor Gott treten.",
    "h": "",
    "o": 19,
    "l": "19"
  },
  {
    "id": "62003020",
    "b": 62,
    "c": 3,
    "v": 20,
    "t": "Doch auch wenn unser Gewissen uns schuldig spricht, dürfen wir darauf vertrauen, dass Gott barmherziger mit uns ist als wir selbst. Er kennt uns ganz genau.",
    "h": "",
    "o": 20,
    "l": "20"
  },
  {
    "id": "62003021",
    "b": 62,
    "c": 3,
    "v": 21,
    "t": "Kann uns also unser Gewissen nicht mehr verurteilen, meine Lieben, dann dürfen wir voller Freude und Zuversicht zu Gott kommen.",
    "h": "",
    "o": 21,
    "l": "21"
  },
  {
    "id": "62003022",
    "b": 62,
    "c": 3,
    "v": 22,
    "t": "Er wird uns geben, worum wir ihn bitten; denn wir richten uns nach seinen Geboten und leben, wie es ihm gefällt.",
    "h": "",
    "o": 22,
    "l": "22"
  },
  {
    "id": "62003023",
    "b": 62,
    "c": 3,
    "v": 23,
    "t": "Und so lautet Gottes Gebot: Wir sollen an seinen Sohn Jesus Christus glauben und einander so lieben, wie Christus es uns aufgetragen hat.",
    "h": "",
    "o": 23,
    "l": "23"
  },
  {
    "id": "62003024",
    "b": 62,
    "c": 3,
    "v": 24,
    "t": "Wer sich an seine Gebote hält, der bleibt mit Gott verbunden und Gott mit ihm. Wir wissen, dass Gott in uns lebt; das bestätigt uns der Geist, den er uns geschenkt hat.",
    "h": "",
    "o": 24,
    "l": "24"
  },
  {
    "id": "62004001",
    "b": 62,
    "c": 4,
    "v": 1,
    "t": "Glaubt nicht jedem, der behauptet, dass Gottes Geist durch ihn redet. Prüft vielmehr genau, ob das, was er sagt, wirklich von Gottes Geist stammt. Denn in dieser Welt verbreiten viele falsche Propheten ihre Irrlehren.",
    "h": "Die Liebe Gottes und der Glaube an Jesus Christus: ihre Auswirkungen\n(Kapitel 4–5)\nDer Geist der Wahrheit und der Geist der Lüge",
    "o": 1,
    "l": "1"
  },
  {
    "id": "62004002",
    "b": 62,
    "c": 4,
    "v": 2,
    "t": "Den Geist Gottes erkennt ihr daran: Er bekennt, dass Jesus Christus als Mensch aus Fleisch und Blut zu uns gekommen ist.",
    "h": "",
    "o": 2,
    "l": "2"
  },
  {
    "id": "62004003",
    "b": 62,
    "c": 4,
    "v": 3,
    "t": "Jemand, der das leugnet, hat nicht den Geist Gottes, sondern aus ihm spricht der Geist des Antichristen. Dass dieser kommen wird, habt ihr schon gehört, ja, er ist schon jetzt in der Welt.",
    "h": "",
    "o": 3,
    "l": "3"
  },
  {
    "id": "62004004",
    "b": 62,
    "c": 4,
    "v": 4,
    "t": "Doch ihr, meine geliebten Kinder, gehört zu Gott. Ihr habt diese Lügenpropheten durchschaut und überwunden. Denn Gott, der in euch wirkt, ist stärker als der Teufel, von dem die Welt beherrscht wird.",
    "h": "",
    "o": 4,
    "l": "4"
  },
  {
    "id": "62004005",
    "b": 62,
    "c": 4,
    "v": 5,
    "t": "Die falschen Propheten gehören ganz zu dieser Welt. Deshalb verbreiten sie nichts als menschliche Vorstellungen und Gedanken, und alle Welt hört auf sie.",
    "h": "",
    "o": 5,
    "l": "5"
  },
  {
    "id": "62004006",
    "b": 62,
    "c": 4,
    "v": 6,
    "t": "Wir dagegen gehören zu Gott. Jeder, der Gott kennt, wird auf uns hören. Wer aber nicht zu Gott gehört, wird uns ablehnen. Daran erkennen wir den Geist der Wahrheit und den Geist der Täuschung.",
    "h": "",
    "o": 6,
    "l": "6"
  },
  {
    "id": "62004007",
    "b": 62,
    "c": 4,
    "v": 7,
    "t": "Meine Freunde! Lasst uns einander lieben, denn die Liebe kommt von Gott. Wer liebt, ist ein Kind Gottes und kennt Gott.",
    "h": "Gottes Liebe und die Liebe zum Mitmenschen",
    "o": 7,
    "l": "7"
  },
  {
    "id": "62004008",
    "b": 62,
    "c": 4,
    "v": 8,
    "t": "Wer aber nicht liebt, der kennt Gott nicht; denn Gott ist Liebe.",
    "h": "",
    "o": 8,
    "l": "8"
  },
  {
    "id": "62004009",
    "b": 62,
    "c": 4,
    "v": 9,
    "t": "Gottes Liebe zu uns ist für alle sichtbar geworden, als er seinen einzigen Sohn in die Welt sandte, damit wir durch ihn leben können.",
    "h": "",
    "o": 9,
    "l": "9"
  },
  {
    "id": "62004010",
    "b": 62,
    "c": 4,
    "v": 10,
    "t": "Das Einzigartige an dieser Liebe ist: Nicht wir haben Gott geliebt, sondern er hat uns seine Liebe geschenkt. Er gab uns seinen Sohn, der alle Sünden auf sich nahm und sie gesühnt hat.",
    "h": "",
    "o": 10,
    "l": "10"
  },
  {
    "id": "62004011",
    "b": 62,
    "c": 4,
    "v": 11,
    "t": "Meine Freunde, wenn uns Gott so sehr geliebt hat, dann müssen auch wir einander lieben.",
    "h": "",
    "o": 11,
    "l": "11"
  },
  {
    "id": "62004012",
    "b": 62,
    "c": 4,
    "v": 12,
    "t": "Niemand hat Gott jemals gesehen. Doch wenn wir einander lieben, bleibt Gott in uns und seine Liebe ist in uns zum Ziel gekommen.",
    "h": "",
    "o": 12,
    "l": "12"
  },
  {
    "id": "62004013",
    "b": 62,
    "c": 4,
    "v": 13,
    "t": "Ich sage es noch einmal: Dass wir mit Gott verbunden bleiben und er mit uns, wissen wir, weil er uns seinen Geist gegeben hat.",
    "h": "",
    "o": 13,
    "l": "13"
  },
  {
    "id": "62004014",
    "b": 62,
    "c": 4,
    "v": 14,
    "t": "Außerdem haben wir es selbst erlebt und können bezeugen, dass Gott, der Vater, seinen Sohn in diese Welt gesandt hat, um sie zu retten.",
    "h": "",
    "o": 14,
    "l": "14"
  },
  {
    "id": "62004015",
    "b": 62,
    "c": 4,
    "v": 15,
    "t": "Und wer bekennt, dass Jesus der Sohn Gottes ist, der bleibt in Gott und Gott in ihm.",
    "h": "",
    "o": 15,
    "l": "15"
  },
  {
    "id": "62004016",
    "b": 62,
    "c": 4,
    "v": 16,
    "t": "Wir haben erkannt, dass Gott uns liebt, und wir vertrauen fest auf diese Liebe. Gott ist Liebe, und wer in dieser Liebe bleibt, der bleibt in Gott und Gott in ihm.",
    "h": "",
    "o": 16,
    "l": "16"
  },
  {
    "id": "62004017",
    "b": 62,
    "c": 4,
    "v": 17,
    "t": "Darin hat Gottes Liebe ihr Ziel erreicht, so dass wir dem Tag des Gerichts voller Zuversicht entgegengehen können. Denn wir sind in dieser Welt schon ebenso mit dem Vater verbunden, wie Christus es ist.",
    "h": "",
    "o": 17,
    "l": "17"
  },
  {
    "id": "62004018",
    "b": 62,
    "c": 4,
    "v": 18,
    "t": "Wirkliche Liebe ist frei von Angst. Ja, wenn Gottes vollkommene Liebe uns erfüllt, vertreibt sie sogar die Angst. Wer sich also fürchtet und vor der Strafe zittert, bei dem ist Gottes Liebe noch nicht zum Ziel gekommen.",
    "h": "",
    "o": 18,
    "l": "18"
  },
  {
    "id": "62004019",
    "b": 62,
    "c": 4,
    "v": 19,
    "t": "Wir lieben, weil Gott uns zuerst geliebt hat.",
    "h": "",
    "o": 19,
    "l": "19"
  },
  {
    "id": "62004020",
    "b": 62,
    "c": 4,
    "v": 20,
    "t": "Sollte nun jemand behaupten: »Ich liebe Gott«, und dabei seinen Bruder oder seine Schwester hassen, dann ist er ein Lügner. Wenn er schon seine Geschwister nicht liebt, die er sehen kann, wie will er dann Gott lieben, den er nicht sieht?",
    "h": "",
    "o": 20,
    "l": "20"
  },
  {
    "id": "62004021",
    "b": 62,
    "c": 4,
    "v": 21,
    "t": "Vergesst nicht, dass Gott selbst uns aufgetragen hat: Wer Gott liebt, der muss auch seinen Bruder und seine Schwester lieben.",
    "h": "",
    "o": 21,
    "l": "21"
  },
  {
    "id": "62005001",
    "b": 62,
    "c": 5,
    "v": 1,
    "t": "Wer glaubt, dass Jesus der von Gott versprochene Retter ist, der ist ein Kind Gottes. Kinder aber, die ihren Vater lieben, die lieben auch ihre Brüder und Schwestern.",
    "h": "Ein Glaube, der Widerstände überwindet",
    "o": 1,
    "l": "1"
  },
  {
    "id": "62005002",
    "b": 62,
    "c": 5,
    "v": 2,
    "t": "Und umgekehrt gilt: Dass wir wirklich Gottes Kinder lieben, erkennen wir an unserer Liebe zu Gott und daran, dass wir nach seinen Geboten leben.",
    "h": "",
    "o": 2,
    "l": "2"
  },
  {
    "id": "62005003",
    "b": 62,
    "c": 5,
    "v": 3,
    "t": "Denn Gott lieben heißt nichts anderes als seine Gebote befolgen; und seine Gebote sind nicht schwer.",
    "h": "",
    "o": 3,
    "l": "3"
  },
  {
    "id": "62005004",
    "b": 62,
    "c": 5,
    "v": 4,
    "t": "Jedes Kind Gottes kann den Sieg erringen über alles, was sich in dieser Welt Gott widersetzt. Ja, unser Glaube hat diese Welt bereits besiegt.",
    "h": "",
    "o": 4,
    "l": "4"
  },
  {
    "id": "62005005",
    "b": 62,
    "c": 5,
    "v": 5,
    "t": "Denn nur wer daran glaubt, dass Jesus der Sohn Gottes ist, kann diesen Sieg erringen.",
    "h": "",
    "o": 5,
    "l": "5"
  },
  {
    "id": "62005006",
    "b": 62,
    "c": 5,
    "v": 6,
    "t": "Jesus Christus kam zu uns. Er wurde getauft und hat sein Blut für uns am Kreuz vergossen. Nicht allein das Wasser seiner Taufe, sondern auch sein Blut bestätigen ihn als Sohn Gottes. Das bezeugt auch Gottes Geist, und Gottes Geist ist die Wahrheit.",
    "h": "Drei Zeugen für Jesus Christus",
    "o": 6,
    "l": "6"
  },
  {
    "id": "62005007",
    "b": 62,
    "c": 5,
    "v": 7,
    "t": "Für Jesus Christus als den Sohn Gottes sprechen also drei Zeugen:",
    "h": "",
    "o": 7,
    "l": "7"
  },
  {
    "id": "62005008",
    "b": 62,
    "c": 5,
    "v": 8,
    "t": "Gottes Geist, das Wasser der Taufe und das Blut, das Jesus am Kreuz vergossen hat. Alle drei Zeugen stimmen in ihrer Aussage völlig überein.",
    "h": "",
    "o": 8,
    "l": "8"
  },
  {
    "id": "62005009",
    "b": 62,
    "c": 5,
    "v": 9,
    "t": "Wenn wir schon den Zeugenaussagen von Menschen Glauben schenken, wie viel mehr müssen wir dann dem vertrauen, was Gott selbst bezeugt. Und Gott hat bezeugt, dass Jesus Christus sein Sohn ist.",
    "h": "",
    "o": 9,
    "l": "9"
  },
  {
    "id": "62005010",
    "b": 62,
    "c": 5,
    "v": 10,
    "t": "Wer an den Sohn Gottes glaubt, der ist in seinem Innersten von der Wahrheit dieser Aussage überzeugt. Wer Gott nicht glaubt, stellt ihn als Lügner hin; denn er behauptet ja, Gottes Aussage über Jesus Christus sei falsch.",
    "h": "",
    "o": 10,
    "l": "10"
  },
  {
    "id": "62005011",
    "b": 62,
    "c": 5,
    "v": 11,
    "t": "Gott aber hat damit ganz eindeutig bestätigt, dass er uns das ewige Leben schenkt, und zwar nur durch seinen Sohn.",
    "h": "",
    "o": 11,
    "l": "11"
  },
  {
    "id": "62005012",
    "b": 62,
    "c": 5,
    "v": 12,
    "t": "Wer also mit dem Sohn verbunden ist, der hat das Leben. Wer aber keine Gemeinschaft mit dem Sohn hat, der hat auch das Leben nicht.",
    "h": "",
    "o": 12,
    "l": "12"
  },
  {
    "id": "62005013",
    "b": 62,
    "c": 5,
    "v": 13,
    "t": "Ich weiß, dass ihr an Jesus Christus als den Sohn Gottes glaubt. Mein Brief sollte euch noch einmal versichern, dass ihr das ewige Leben habt.",
    "h": "Gott erhört unsere Gebete",
    "o": 13,
    "l": "13"
  },
  {
    "id": "62005014",
    "b": 62,
    "c": 5,
    "v": 14,
    "t": "Deshalb dürfen wir uns auch darauf verlassen, dass Gott unser Beten erhört, wenn wir ihn um etwas bitten, was seinem Willen entspricht.",
    "h": "",
    "o": 14,
    "l": "14"
  },
  {
    "id": "62005015",
    "b": 62,
    "c": 5,
    "v": 15,
    "t": "Und weil wir wissen, dass Gott all unsere Gebete hört, dürfen wir sicher sein, dass er uns gibt, worum wir ihn bitten. Es ist, als hätten wir es schon erhalten.",
    "h": "",
    "o": 15,
    "l": "15"
  },
  {
    "id": "62005016",
    "b": 62,
    "c": 5,
    "v": 16,
    "t": "Wenn jemand von euch merkt, dass ein anderer Christ eine Sünde begeht, die nicht zum Tod führt, soll er für ihn beten. Dann wird Gott diesem Menschen das Leben schenken. Das gilt aber nicht für die Sünde, die den Tod zur Folge hat. Wenn jemand diese Schuld auf sich lädt, sollt ihr nicht für ihn beten.",
    "h": "",
    "o": 16,
    "l": "16"
  },
  {
    "id": "62005017",
    "b": 62,
    "c": 5,
    "v": 17,
    "t": "Natürlich ist jedes Unrecht Sünde. Aber nicht jede Sünde führt in den Tod.",
    "h": "",
    "o": 17,
    "l": "17"
  },
  {
    "id": "62005018",
    "b": 62,
    "c": 5,
    "v": 18,
    "t": "Wir wissen: Wer ein Kind Gottes ist, der sündigt nicht, weil der Sohn Gottes ihn bewahrt. Darum kann der Teufel ihm nichts anhaben.",
    "h": "",
    "o": 18,
    "l": "18"
  },
  {
    "id": "62005019",
    "b": 62,
    "c": 5,
    "v": 19,
    "t": "Wir wissen auch, dass wir zu Gott gehören, auch wenn die ganze Welt um uns herum vom Teufel beherrscht wird.",
    "h": "",
    "o": 19,
    "l": "19"
  },
  {
    "id": "62005020",
    "b": 62,
    "c": 5,
    "v": 20,
    "t": "Und wir wissen: Der Sohn Gottes ist zu uns gekommen, damit wir durch ihn Gott kennen lernen, der die Wahrheit ist. Nun sind wir eng mit dem wahren Gott verbunden, weil wir mit seinem Sohn Jesus Christus verbunden sind. Ja, Jesus Christus ist selbst der wahre Gott. Er ist das ewige Leben.",
    "h": "",
    "o": 20,
    "l": "20"
  },
  {
    "id": "62005021",
    "b": 62,
    "c": 5,
    "v": 21,
    "t": "Darum, meine Kinder, hütet euch davor, anderen Göttern nachzulaufen!",
    "h": "",
    "o": 21,
    "l": "21"
  }
]