[
  {
    "id": "17001001",
    "b": 17,
    "c": 1,
    "v": 1,
    "t": "The words of Amos, who was among the shepherds of Tekoa; the word which he saw concerning Israel in the days of Uzziah king of Judah, and in the days of Jeroboam the son of Joash king of Israel, two years before the earthquake.",
    "h": "CHAPTER ONE",
    "o": 1,
    "l": "1"
  },
  {
    "id": "17001002",
    "b": 17,
    "c": 1,
    "v": 2,
    "t": "And he said, “The Lord will roar from Zion and utter His voice from Jerusalem; and the pastures of the shepherds shall mourn, and the top of Carmel shall dry up.”",
    "h": "",
    "o": 2,
    "l": "2"
  },
  {
    "id": "17001003",
    "b": 17,
    "c": 1,
    "v": 3,
    "t": "Thus says the Lord, “For three transgressions of Damascus, yea for four, I will not turn away its punishment; because they have threshed Gilead with threshing instruments of iron.",
    "h": "",
    "o": 3,
    "l": "3"
  },
  {
    "id": "17001004",
    "b": 17,
    "c": 1,
    "v": 4,
    "t": "But I will send a fire into the house of Hazael, which shall devour the palaces of Ben-Hadad.",
    "h": "",
    "o": 4,
    "l": "4"
  },
  {
    "id": "17001005",
    "b": 17,
    "c": 1,
    "v": 5,
    "t": "I will also break the gate bar of Damascus, and cut off the inhabitant from the Valley of Aven, and from him who holds the scepter from the house of Eden. And the people of Syria shall go into captivity to Kir,” says the Lord.",
    "h": "",
    "o": 5,
    "l": "5"
  },
  {
    "id": "17001006",
    "b": 17,
    "c": 1,
    "v": 6,
    "t": "Thus says the Lord, “For three transgressions of Gaza, yea for four, I will not turn away its punishment; because they deported the children of Judah as exiles to deliver them up to Edom.",
    "h": "",
    "o": 6,
    "l": "6"
  },
  {
    "id": "17001007",
    "b": 17,
    "c": 1,
    "v": 7,
    "t": "But I will send a fire on the wall of Gaza, which shall devour its palaces.",
    "h": "",
    "o": 7,
    "l": "7"
  },
  {
    "id": "17001008",
    "b": 17,
    "c": 1,
    "v": 8,
    "t": "And I will cut off the people from Ashdod, and him who holds the scepter from Ashkelon, and I will turn My hand against Ekron. And the rest of the Philistines shall perish,” says the Lord God.",
    "h": "",
    "o": 8,
    "l": "8"
  },
  {
    "id": "17001009",
    "b": 17,
    "c": 1,
    "v": 9,
    "t": "Thus says the Lord, “For three transgressions of Tyre, yea for four, I will not turn away its punishment. Because they delivered up the children of Judah as exiles to Edom, and did not remember the brotherly covenant.",
    "h": "",
    "o": 9,
    "l": "9"
  },
  {
    "id": "17001010",
    "b": 17,
    "c": 1,
    "v": 10,
    "t": "But I will send a fire upon the wall of Tyre, which shall devour its palaces.”",
    "h": "",
    "o": 10,
    "l": "10"
  },
  {
    "id": "17001011",
    "b": 17,
    "c": 1,
    "v": 11,
    "t": "Thus says the Lord, “For three transgressions of Edom, yea for four, I will not turn away its punishment. Because he pursued his brother with the sword, and cast off all mercy, and his anger raged perpetually, and he kept his wrath forever.",
    "h": "",
    "o": 11,
    "l": "11"
  },
  {
    "id": "17001012",
    "b": 17,
    "c": 1,
    "v": 12,
    "t": "But I will send a fire upon Teman, which shall devour the palaces of Bozrah.”",
    "h": "",
    "o": 12,
    "l": "12"
  },
  {
    "id": "17001013",
    "b": 17,
    "c": 1,
    "v": 13,
    "t": "Thus says the Lord, “For three transgressions of the children of Ammon, yea for four, I will not turn away its punishment. Because they have ripped up the pregnant women of Gilead, to make their own border larger.",
    "h": "",
    "o": 13,
    "l": "13"
  },
  {
    "id": "17001014",
    "b": 17,
    "c": 1,
    "v": 14,
    "t": "But I will kindle a fire in the wall of Rabbah, and it shall devour its palaces with shouting in the day of battle, with a tempest in the day of the whirlwind.",
    "h": "",
    "o": 14,
    "l": "14"
  },
  {
    "id": "17001015",
    "b": 17,
    "c": 1,
    "v": 15,
    "t": "And their king shall go into captivity, he and his princes together,” says the Lord.",
    "h": "",
    "o": 15,
    "l": "15"
  },
  {
    "id": "17002001",
    "b": 17,
    "c": 2,
    "v": 1,
    "t": "Thus says the Lord, “For three transgressions of Moab, yea for four, I will not turn away its punishment; because he burned the bones of the king of Edom into lime.",
    "h": "CHAPTER TWO",
    "o": 1,
    "l": "1"
  },
  {
    "id": "17002002",
    "b": 17,
    "c": 2,
    "v": 2,
    "t": "But I will send a fire upon Moab, and it shall devour the palaces of Kerioth. And Moab shall die with great noise, with shouting, with the sound of a ram’s horn.",
    "h": "",
    "o": 2,
    "l": "2"
  },
  {
    "id": "17002003",
    "b": 17,
    "c": 2,
    "v": 3,
    "t": "And I will cut off the judge from its midst, and will slay all its princes with him,” says the Lord.",
    "h": "",
    "o": 3,
    "l": "3"
  },
  {
    "id": "17002004",
    "b": 17,
    "c": 2,
    "v": 4,
    "t": "Thus says the Lord, “For three transgressions of Judah, yea for four, I will not turn away its punishment; because they have despised the laws of the Lord, and have not kept His commandments. And their lies caused them to err, those after which their fathers walked.",
    "h": "",
    "o": 4,
    "l": "4"
  },
  {
    "id": "17002005",
    "b": 17,
    "c": 2,
    "v": 5,
    "t": "But I will send a fire upon Judah, and it shall devour the palaces of Jerusalem.”",
    "h": "",
    "o": 5,
    "l": "5"
  },
  {
    "id": "17002006",
    "b": 17,
    "c": 2,
    "v": 6,
    "t": "Thus says the Lord, “For three transgressions of Israel, yea for four, I will not turn away its punishment; because they sold the righteous for silver, and the poor for a pair of sandals;",
    "h": "",
    "o": 6,
    "l": "6"
  },
  {
    "id": "17002007",
    "b": 17,
    "c": 2,
    "v": 7,
    "t": "They trample the head of the poor into the dust of the earth, and turn aside the way of the meek. And a man and his father will go in to the same woman, to defile My holy name.",
    "h": "",
    "o": 7,
    "l": "7"
  },
  {
    "id": "17002008",
    "b": 17,
    "c": 2,
    "v": 8,
    "t": "And beside every altar they lay themselves down upon garments taken in pledge, and they drink the wine of the condemned in the house of their god.",
    "h": "",
    "o": 8,
    "l": "8"
  },
  {
    "id": "17002009",
    "b": 17,
    "c": 2,
    "v": 9,
    "t": "Yet I destroyed the Amorite before them, whose height was like the height of the cedars, and whose strength was as the oaks; yet I destroyed his fruit from above and his roots from below.",
    "h": "",
    "o": 9,
    "l": "9"
  },
  {
    "id": "17002010",
    "b": 17,
    "c": 2,
    "v": 10,
    "t": "Also I brought you up from the land of Egypt and led you forty years through the wilderness to possess the land of the Amorite.",
    "h": "",
    "o": 10,
    "l": "10"
  },
  {
    "id": "17002011",
    "b": 17,
    "c": 2,
    "v": 11,
    "t": "And I raised up prophets from your sons and Nazarites from your young men. Is it not even so, O children of Israel?” says the Lord.",
    "h": "",
    "o": 11,
    "l": "11"
  },
  {
    "id": "17002012",
    "b": 17,
    "c": 2,
    "v": 12,
    "t": "“But you gave the Nazarites wine to drink, and commanded the prophets, saying, ‘Do not prophesy.’",
    "h": "",
    "o": 12,
    "l": "12"
  },
  {
    "id": "17002013",
    "b": 17,
    "c": 2,
    "v": 13,
    "t": "Behold, I will press you down, as a cart full of sheaves is pressed down.",
    "h": "",
    "o": 13,
    "l": "13"
  },
  {
    "id": "17002014",
    "b": 17,
    "c": 2,
    "v": 14,
    "t": "Therefore the flight shall perish from the swift, and the strong shall not strengthen his power, nor shall the mighty deliver his life;",
    "h": "",
    "o": 14,
    "l": "14"
  },
  {
    "id": "17002015",
    "b": 17,
    "c": 2,
    "v": 15,
    "t": "Nor shall he who handles the bow stand. And the swift-footed shall not deliver himself; neither shall he that rides the horse deliver himself.",
    "h": "",
    "o": 15,
    "l": "15"
  },
  {
    "id": "17002016",
    "b": 17,
    "c": 2,
    "v": 16,
    "t": "And the stout-hearted among the mighty shall flee away naked in that day,” says the Lord.",
    "h": "",
    "o": 16,
    "l": "16"
  },
  {
    "id": "17003001",
    "b": 17,
    "c": 3,
    "v": 1,
    "t": "Hear this word that the Lord has spoken against you, children of Israel, against the whole family which I brought up from the land of Egypt, saying,",
    "h": "CHAPTER THREE",
    "o": 1,
    "l": "1"
  },
  {
    "id": "17003002",
    "b": 17,
    "c": 3,
    "v": 2,
    "t": "“You only have I known of all the families of the earth; therefore I will punish you for all your iniquities.",
    "h": "",
    "o": 2,
    "l": "2"
  },
  {
    "id": "17003003",
    "b": 17,
    "c": 3,
    "v": 3,
    "t": "Can two walk together unless they be agreed?",
    "h": "",
    "o": 3,
    "l": "3"
  },
  {
    "id": "17003004",
    "b": 17,
    "c": 3,
    "v": 4,
    "t": "Will a lion roar in the forest when he has no prey? Will a young lion cry out of his den if he has caught nothing?",
    "h": "",
    "o": 4,
    "l": "4"
  },
  {
    "id": "17003005",
    "b": 17,
    "c": 3,
    "v": 5,
    "t": "Will a bird fall into a trap on the ground, when there is no bait for it? Will a trap spring up from the ground, and nothing at all be caught?",
    "h": "",
    "o": 5,
    "l": "5"
  },
  {
    "id": "17003006",
    "b": 17,
    "c": 3,
    "v": 6,
    "t": "If a ram’s horn is blown in a city, will the people not also tremble? If there is a calamity in a city, has the Lord not also done it?",
    "h": "",
    "o": 6,
    "l": "6"
  },
  {
    "id": "17003007",
    "b": 17,
    "c": 3,
    "v": 7,
    "t": "Surely the Lord God will do nothing unless He reveals His secret unto His servants the prophets.",
    "h": "",
    "o": 7,
    "l": "7"
  },
  {
    "id": "17003008",
    "b": 17,
    "c": 3,
    "v": 8,
    "t": "The lion has roared—who will not fear? The Lord God has spoken—who can but prophesy?",
    "h": "",
    "o": 8,
    "l": "8"
  },
  {
    "id": "17003009",
    "b": 17,
    "c": 3,
    "v": 9,
    "t": "Make it heard at the palaces of Ashdod, and the palaces in the land of Egypt, and say, ‘Gather yourselves on the mountains of Samaria, and behold the great tumults in its midst, and the oppressed within it,",
    "h": "",
    "o": 9,
    "l": "9"
  },
  {
    "id": "17003010",
    "b": 17,
    "c": 3,
    "v": 10,
    "t": "For they do not know to do right,’ says the Lord, ‘those who store up violence and robbery in their palaces.’ ”",
    "h": "",
    "o": 10,
    "l": "10"
  },
  {
    "id": "17003011",
    "b": 17,
    "c": 3,
    "v": 11,
    "t": "Therefore thus says the Lord God, “An enemy! And he shall be all around the land; and he shall bring you down from your strength, and your palaces shall be plundered.”",
    "h": "",
    "o": 11,
    "l": "11"
  },
  {
    "id": "17003012",
    "b": 17,
    "c": 3,
    "v": 12,
    "t": "Thus says the Lord, “As the shepherd takes two legs out of the mouth of the lion, or a piece of an ear, so shall the children of Israel be taken out—those who dwell in Samaria in the corner of a bed, and in Damascus on a couch.",
    "h": "",
    "o": 12,
    "l": "12"
  },
  {
    "id": "17003013",
    "b": 17,
    "c": 3,
    "v": 13,
    "t": "Hear and testify in the house of Jacob,” says the Lord God, the God of hosts,",
    "h": "",
    "o": 13,
    "l": "13"
  },
  {
    "id": "17003014",
    "b": 17,
    "c": 3,
    "v": 14,
    "t": "“For in the day that I shall visit the transgressions of Israel on him, I will also visit the altars of Bethel. And the horns of the altar shall be cut off and shall fall to the ground.",
    "h": "",
    "o": 14,
    "l": "14"
  },
  {
    "id": "17003015",
    "b": 17,
    "c": 3,
    "v": 15,
    "t": "And I will strike the winter house together with the summer house, and the houses of ivory shall perish. And the great houses shall be swept away,” says the Lord.",
    "h": "",
    "o": 15,
    "l": "15"
  },
  {
    "id": "17004001",
    "b": 17,
    "c": 4,
    "v": 1,
    "t": "Hear this word, cows of Bashan who are in the mountain of Samaria—who oppress the poor, who crush the needy, who say to their husbands, “Bring in wine that we may drink.”",
    "h": "CHAPTER FOUR",
    "o": 1,
    "l": "1"
  },
  {
    "id": "17004002",
    "b": 17,
    "c": 4,
    "v": 2,
    "t": "The Lord God has sworn by His holiness, “Behold, the days shall come upon you when they will lift you up with meat hooks, and your posterity with fishhooks.",
    "h": "",
    "o": 2,
    "l": "2"
  },
  {
    "id": "17004003",
    "b": 17,
    "c": 4,
    "v": 3,
    "t": "And you shall go out at the breaches in the walls, each woman straight before her. And you shall be cast off to Harmon,” says the Lord.",
    "h": "",
    "o": 3,
    "l": "3"
  },
  {
    "id": "17004004",
    "b": 17,
    "c": 4,
    "v": 4,
    "t": "“Come to Bethel and transgress; to Gilgal and multiply transgressing at Gilgal. And bring your sacrifices for the morning, your tithes for three years;",
    "h": "",
    "o": 4,
    "l": "4"
  },
  {
    "id": "17004005",
    "b": 17,
    "c": 4,
    "v": 5,
    "t": "And offer a sacrifice of thanksgiving from that which is leavened, and cry out; call out the voluntary offerings, for so you love to do, O children of Israel!” says the Lord God.",
    "h": "",
    "o": 5,
    "l": "5"
  },
  {
    "id": "17004006",
    "b": 17,
    "c": 4,
    "v": 6,
    "t": "“And I also have given you cleanness of teeth in all your cities, and lack of bread in all your places, yet you have not returned to Me,” says the Lord.",
    "h": "",
    "o": 6,
    "l": "6"
  },
  {
    "id": "17004007",
    "b": 17,
    "c": 4,
    "v": 7,
    "t": "“And I have also withheld the rain from you, when there were yet three months to the harvest. And I caused rain to fall on one city and caused it not to rain on another city; one field was rained on, and the field on which it did not rain dried up.",
    "h": "",
    "o": 7,
    "l": "7"
  },
  {
    "id": "17004008",
    "b": 17,
    "c": 4,
    "v": 8,
    "t": "So two or three cities wandered to one city to drink water, but they were not satisfied; yet you have not returned to Me,” says the Lord.",
    "h": "",
    "o": 8,
    "l": "8"
  },
  {
    "id": "17004009",
    "b": 17,
    "c": 4,
    "v": 9,
    "t": "“I have stricken you with blasting and mildew. When your gardens and your vineyards, and your fig trees, and your olive trees increased, the creeping locust devoured them; yet you have not returned to Me,” says the Lord.",
    "h": "",
    "o": 9,
    "l": "9"
  },
  {
    "id": "17004010",
    "b": 17,
    "c": 4,
    "v": 10,
    "t": "“I have sent the plague among you after the manner of Egypt; I have slain your young men with the sword, and have taken away your horses. And I have made the stench of your camps to come up into your nostrils; yet you have not returned to Me,” says the Lord.",
    "h": "",
    "o": 10,
    "l": "10"
  },
  {
    "id": "17004011",
    "b": 17,
    "c": 4,
    "v": 11,
    "t": "“I have overthrown some among you as God overthrew Sodom and Gomorrah, and you were like a firebrand plucked out of the burning; yet you have not returned to Me,” says the Lord.",
    "h": "",
    "o": 11,
    "l": "11"
  },
  {
    "id": "17004012",
    "b": 17,
    "c": 4,
    "v": 12,
    "t": "“Therefore I will do this to you, O Israel; and because I will do this to you, prepare to meet your God, O Israel!”",
    "h": "",
    "o": 12,
    "l": "12"
  },
  {
    "id": "17004013",
    "b": 17,
    "c": 4,
    "v": 13,
    "t": "For lo, He forms the mountains and creates the wind, and declares to man what his thought is. He who makes the morning darkness, and treads upon the high places of the earth—the Lord, the God of hosts, is His name.",
    "h": "",
    "o": 13,
    "l": "13"
  },
  {
    "id": "17005001",
    "b": 17,
    "c": 5,
    "v": 1,
    "t": "Hear this word which I take up against you, even a lamentation, O house of Israel.",
    "h": "CHAPTER FIVE",
    "o": 1,
    "l": "1"
  },
  {
    "id": "17005002",
    "b": 17,
    "c": 5,
    "v": 2,
    "t": "The virgin of Israel has fallen; she shall rise no more; she lies forsaken on her land. There is none to raise her up,",
    "h": "",
    "o": 2,
    "l": "2"
  },
  {
    "id": "17005003",
    "b": 17,
    "c": 5,
    "v": 3,
    "t": "For thus says the Lord God, “The city that went out by a thousand shall leave a hundred, and that which went out by a hundred shall have ten left in the house of Israel,”",
    "h": "",
    "o": 3,
    "l": "3"
  },
  {
    "id": "17005004",
    "b": 17,
    "c": 5,
    "v": 4,
    "t": "For thus says the Lord to the house of Israel, “Seek Me, and you shall live.",
    "h": "",
    "o": 4,
    "l": "4"
  },
  {
    "id": "17005005",
    "b": 17,
    "c": 5,
    "v": 5,
    "t": "But do not seek Bethel, nor enter into Gilgal, and do not pass to Beersheba; for Gilgal shall surely go into exile, and Bethel shall come to nothing.",
    "h": "",
    "o": 5,
    "l": "5"
  },
  {
    "id": "17005006",
    "b": 17,
    "c": 5,
    "v": 6,
    "t": "Seek the Lord and you shall live, lest He break out like a fire on the house of Joseph and devour it, and there be none to quench it in Bethel—",
    "h": "",
    "o": 6,
    "l": "6"
  },
  {
    "id": "17005007",
    "b": 17,
    "c": 5,
    "v": 7,
    "t": "You who turn judgment to wormwood and leave off righteousness in the earth!”",
    "h": "",
    "o": 7,
    "l": "7"
  },
  {
    "id": "17005008",
    "b": 17,
    "c": 5,
    "v": 8,
    "t": "Seek Him Who created the Pleiades and Orion, and Who turned the deep darkness into the morning, and Him Who darkened the day into night. Seek Him Who calls for the waters of the sea, and pours them out on the face of the earth—the Lord is His name,",
    "h": "",
    "o": 8,
    "l": "8"
  },
  {
    "id": "17005009",
    "b": 17,
    "c": 5,
    "v": 9,
    "t": "Who causes destruction to flash out against the strong, and destruction against the fortress.",
    "h": "",
    "o": 9,
    "l": "9"
  },
  {
    "id": "17005010",
    "b": 17,
    "c": 5,
    "v": 10,
    "t": "They hate him who rebukes in the gate, and they despise him who speaks uprightly.",
    "h": "",
    "o": 10,
    "l": "10"
  },
  {
    "id": "17005011",
    "b": 17,
    "c": 5,
    "v": 11,
    "t": "Therefore—because of your trampling upon the poor, and because you take tribute of grain from him—though you have built houses of carved stone, you shall not dwell in them; though you have planted desirable vineyards, you shall not drink wine from them,",
    "h": "",
    "o": 11,
    "l": "11"
  },
  {
    "id": "17005012",
    "b": 17,
    "c": 5,
    "v": 12,
    "t": "For I know your many transgressions and your many sins. They afflict the just, they take a bribe, and they turn aside the poor in the gate.",
    "h": "",
    "o": 12,
    "l": "12"
  },
  {
    "id": "17005013",
    "b": 17,
    "c": 5,
    "v": 13,
    "t": "Therefore the prudent shall keep silent in that time; for it is an evil time.",
    "h": "",
    "o": 13,
    "l": "13"
  },
  {
    "id": "17005014",
    "b": 17,
    "c": 5,
    "v": 14,
    "t": "Seek good and not evil, that you may live; and so the Lord, the God of hosts, shall be with you, as you have spoken.",
    "h": "",
    "o": 14,
    "l": "14"
  },
  {
    "id": "17005015",
    "b": 17,
    "c": 5,
    "v": 15,
    "t": "Hate the evil, and love the good, and establish judgment in the gate. It may be that the Lord God of hosts will be gracious to the remnant of Joseph.",
    "h": "",
    "o": 15,
    "l": "15"
  },
  {
    "id": "17005016",
    "b": 17,
    "c": 5,
    "v": 16,
    "t": "Therefore the Lord, the God of hosts, the Master, says this, “Wailing shall be in all streets; and they shall say in all the highways, ‘Alas! Alas!’ And they shall call the tiller to mourning, and those who are skillful in mourning to wailing.",
    "h": "",
    "o": 16,
    "l": "16"
  },
  {
    "id": "17005017",
    "b": 17,
    "c": 5,
    "v": 17,
    "t": "And there shall be wailing in all vineyards; for I will pass through you,” says the Lord.",
    "h": "",
    "o": 17,
    "l": "17"
  },
  {
    "id": "17005018",
    "b": 17,
    "c": 5,
    "v": 18,
    "t": "Woe to those desiring the day of the Lord ! What is this for you? The day of the Lord is darkness and not light;",
    "h": "",
    "o": 18,
    "l": "18"
  },
  {
    "id": "17005019",
    "b": 17,
    "c": 5,
    "v": 19,
    "t": "As if a man fled from a lion, and a bear met him; or went into the house and leaned his hand on the wall, and a snake bit him.",
    "h": "",
    "o": 19,
    "l": "19"
  },
  {
    "id": "17005020",
    "b": 17,
    "c": 5,
    "v": 20,
    "t": "Shall not the day of the Lord be darkness and not light? Even very dark, and no brightness in it?",
    "h": "",
    "o": 20,
    "l": "20"
  },
  {
    "id": "17005021",
    "b": 17,
    "c": 5,
    "v": 21,
    "t": "“I hate, I despise your feast days, and I will take no delight in your solemn assemblies.",
    "h": "",
    "o": 21,
    "l": "21"
  },
  {
    "id": "17005022",
    "b": 17,
    "c": 5,
    "v": 22,
    "t": "Though you offer Me burnt offerings and your grain offerings, I will not accept them. Nor will I regard the peace offerings of your fat animals.",
    "h": "",
    "o": 22,
    "l": "22"
  },
  {
    "id": "17005023",
    "b": 17,
    "c": 5,
    "v": 23,
    "t": "Take the noise of your songs away from Me; for I will not hear the melody of your harps.",
    "h": "",
    "o": 23,
    "l": "23"
  },
  {
    "id": "17005024",
    "b": 17,
    "c": 5,
    "v": 24,
    "t": "But let judgment roll down like waters, and righteousness like a mighty stream.",
    "h": "",
    "o": 24,
    "l": "24"
  },
  {
    "id": "17005025",
    "b": 17,
    "c": 5,
    "v": 25,
    "t": "Have you offered sacrifices and offerings to Me forty years in the wilderness, O house of Israel?",
    "h": "",
    "o": 25,
    "l": "25"
  },
  {
    "id": "17005026",
    "b": 17,
    "c": 5,
    "v": 26,
    "t": "But now you have carried the tabernacle of your Moloch and Chiun, your images, the star of your gods which you made for yourselves.",
    "h": "",
    "o": 26,
    "l": "26"
  },
  {
    "id": "17005027",
    "b": 17,
    "c": 5,
    "v": 27,
    "t": "So I will cause you to go into exile beyond Damascus,” says the Lord, Whose name is the God of hosts.",
    "h": "",
    "o": 27,
    "l": "27"
  },
  {
    "id": "17006001",
    "b": 17,
    "c": 6,
    "v": 1,
    "t": "Woe to those at ease in Zion, and trust in the mountain of Samaria, who are named chief of the nations. And the house of Israel came to them.",
    "h": "CHAPTER SIX",
    "o": 1,
    "l": "1"
  },
  {
    "id": "17006002",
    "b": 17,
    "c": 6,
    "v": 2,
    "t": "Pass over to Calneh, and see; and from there go to Hamath the great. Then go down to Gath of the Philistines. Are they better than these kingdoms, or is their border greater than your border?",
    "h": "",
    "o": 2,
    "l": "2"
  },
  {
    "id": "17006003",
    "b": 17,
    "c": 6,
    "v": 3,
    "t": "You who put the evil day far away, and cause the seat of violence to come near;",
    "h": "",
    "o": 3,
    "l": "3"
  },
  {
    "id": "17006004",
    "b": 17,
    "c": 6,
    "v": 4,
    "t": "Who lie upon beds of ivory, and those sprawling upon their couches, and eating lambs out of the flock, and the calves out of the midst of the stall;",
    "h": "",
    "o": 4,
    "l": "4"
  },
  {
    "id": "17006005",
    "b": 17,
    "c": 6,
    "v": 5,
    "t": "Who sing idle songs to the sound of the harp; and invent instruments of music for themselves, like David;",
    "h": "",
    "o": 5,
    "l": "5"
  },
  {
    "id": "17006006",
    "b": 17,
    "c": 6,
    "v": 6,
    "t": "Who drink wine in bowls, and anoint themselves with the best of oils—but do not grieve for the affliction of Joseph!",
    "h": "",
    "o": 6,
    "l": "6"
  },
  {
    "id": "17006007",
    "b": 17,
    "c": 6,
    "v": 7,
    "t": "Therefore now they shall go into exile with the first of the exiles. And the feasting of those who recline themselves shall cease.",
    "h": "",
    "o": 7,
    "l": "7"
  },
  {
    "id": "17006008",
    "b": 17,
    "c": 6,
    "v": 8,
    "t": "The Lord God has sworn by Himself—thus says the Lord, the God of hosts, “I despise the glory of Jacob, and hate his palaces; and I will shut up the city and all its fullness.",
    "h": "",
    "o": 8,
    "l": "8"
  },
  {
    "id": "17006009",
    "b": 17,
    "c": 6,
    "v": 9,
    "t": "And it shall be if ten men remain in one house, then they shall die.",
    "h": "",
    "o": 9,
    "l": "9"
  },
  {
    "id": "17006010",
    "b": 17,
    "c": 6,
    "v": 10,
    "t": "And a dead man’s uncle shall take him up, and he who burns the bodies, to bring the bones out of the house, and shall say to him left in the recesses of the house, “Are any bodies still with you?” And he shall say, “No.” Then he shall say, “Hold your tongue, for no one shall mention the name of the Lord.”",
    "h": "",
    "o": 10,
    "l": "10"
  },
  {
    "id": "17006011",
    "b": 17,
    "c": 6,
    "v": 11,
    "t": "For, behold, the Lord commands, and He will strike the great house into pieces, and the little house into cracks.",
    "h": "",
    "o": 11,
    "l": "11"
  },
  {
    "id": "17006012",
    "b": 17,
    "c": 6,
    "v": 12,
    "t": "Shall horses run upon the rock? Will one plow there with oxen? For you have turned justice into gall, and the fruit of righteousness into hemlock—",
    "h": "",
    "o": 12,
    "l": "12"
  },
  {
    "id": "17006013",
    "b": 17,
    "c": 6,
    "v": 13,
    "t": "You who rejoice over nothing, who say, “Have we not taken horns to ourselves by our own strength?”",
    "h": "",
    "o": 13,
    "l": "13"
  },
  {
    "id": "17006014",
    "b": 17,
    "c": 6,
    "v": 14,
    "t": "“But behold, I will raise a nation up against you, O house of Israel,” says the Lord, the God of hosts. “And they shall afflict you from the entrance to Hamath to the river of the Arabah.”",
    "h": "",
    "o": 14,
    "l": "14"
  },
  {
    "id": "17007001",
    "b": 17,
    "c": 7,
    "v": 1,
    "t": "The Lord God made me see this: And behold, He is forming locusts at the beginning of the growth of the late grass—even behold, the late grass after the king’s mowings.",
    "h": "CHAPTER SEVEN",
    "o": 1,
    "l": "1"
  },
  {
    "id": "17007002",
    "b": 17,
    "c": 7,
    "v": 2,
    "t": "And it came to pass that when they had made an end of eating the tender plant of the land, then I said, “O Lord God, forgive, I pray You. How can Jacob stand? For he is small.”",
    "h": "",
    "o": 2,
    "l": "2"
  },
  {
    "id": "17007003",
    "b": 17,
    "c": 7,
    "v": 3,
    "t": "The Lord repented for this; “It shall not be,” says the Lord.",
    "h": "",
    "o": 3,
    "l": "3"
  },
  {
    "id": "17007004",
    "b": 17,
    "c": 7,
    "v": 4,
    "t": "The Lord God made me see this: And behold, the Lord God was calling to contend by fire. And it consumed the great deep, and it was devouring part of it.",
    "h": "",
    "o": 4,
    "l": "4"
  },
  {
    "id": "17007005",
    "b": 17,
    "c": 7,
    "v": 5,
    "t": "Then I said, “O Lord God, I pray You, cease. How can Jacob stand? For he is small.”",
    "h": "",
    "o": 5,
    "l": "5"
  },
  {
    "id": "17007006",
    "b": 17,
    "c": 7,
    "v": 6,
    "t": "The Lord repented for this; “This also shall not be,” says the Lord God.",
    "h": "",
    "o": 6,
    "l": "6"
  },
  {
    "id": "17007007",
    "b": 17,
    "c": 7,
    "v": 7,
    "t": "He made me see this: And behold, the Lord was standing upon a wall made by a plumb line, with a plumb line in His hand.",
    "h": "",
    "o": 7,
    "l": "7"
  },
  {
    "id": "17007008",
    "b": 17,
    "c": 7,
    "v": 8,
    "t": "And the Lord said to me, “Amos, what do you see?” And I said, “A plumb line.” Then the Lord said, “Behold, I will set a plumb line in the midst of My people Israel. I will not again pass by them any more.",
    "h": "",
    "o": 8,
    "l": "8"
  },
  {
    "id": "17007009",
    "b": 17,
    "c": 7,
    "v": 9,
    "t": "And the high places of Isaac shall be desolate, and the holy places of Israel shall be laid waste; and I will rise up against the house of Jeroboam with the sword.”",
    "h": "",
    "o": 9,
    "l": "9"
  },
  {
    "id": "17007010",
    "b": 17,
    "c": 7,
    "v": 10,
    "t": "Then Amaziah the priest of Bethel sent to Jeroboam king of Israel, saying, “Amos has plotted against you in the midst of the house of Israel; the land is not able to bear all his words.",
    "h": "",
    "o": 10,
    "l": "10"
  },
  {
    "id": "17007011",
    "b": 17,
    "c": 7,
    "v": 11,
    "t": "For thus Amos says, ‘Jeroboam shall die by the sword, and Israel shall surely go into exile out of his land.’ ”",
    "h": "",
    "o": 11,
    "l": "11"
  },
  {
    "id": "17007012",
    "b": 17,
    "c": 7,
    "v": 12,
    "t": "And Amaziah said to Amos, “O seer, go, flee for yourself into the land of Judah; and eat bread there, and prophesy there.",
    "h": "",
    "o": 12,
    "l": "12"
  },
  {
    "id": "17007013",
    "b": 17,
    "c": 7,
    "v": 13,
    "t": "But do not prophesy again any more at Bethel; for it is the king’s temple, and it is the king’s royal house.”",
    "h": "",
    "o": 13,
    "l": "13"
  },
  {
    "id": "17007014",
    "b": 17,
    "c": 7,
    "v": 14,
    "t": "Then Amos answered and said to Amaziah, “I was no prophet, nor was I a prophet’s son. But I was a shepherd and a gatherer of fruit from sycamore trees.",
    "h": "",
    "o": 14,
    "l": "14"
  },
  {
    "id": "17007015",
    "b": 17,
    "c": 7,
    "v": 15,
    "t": "And the Lord took me from behind the flock, and the Lord said to me, ‘Go, prophesy to My people Israel.’",
    "h": "",
    "o": 15,
    "l": "15"
  },
  {
    "id": "17007016",
    "b": 17,
    "c": 7,
    "v": 16,
    "t": "Now therefore hear the Word of the Lord. You say, ‘Do not prophesy against Israel, and do not drop words against the house of Isaac.’",
    "h": "",
    "o": 16,
    "l": "16"
  },
  {
    "id": "17007017",
    "b": 17,
    "c": 7,
    "v": 17,
    "t": "Therefore thus says the Lord, ‘Your wife shall be a harlot in the city, and your sons and your daughters shall fall by the sword, and your land shall be divided by line. And you shall die in a defiled land; and Israel shall surely go into exile out of his land.’ ”",
    "h": "",
    "o": 17,
    "l": "17"
  },
  {
    "id": "17008001",
    "b": 17,
    "c": 8,
    "v": 1,
    "t": "The Lord God made me see this: And behold, a basket of summer fruit!",
    "h": "CHAPTER EIGHT",
    "o": 1,
    "l": "1"
  },
  {
    "id": "17008002",
    "b": 17,
    "c": 8,
    "v": 2,
    "t": "And He said, “Amos, what do you see?” And I said, “A basket of summer fruit.” Then the Lord said to me, “The end has come to My people Israel: I will not again pass by them any more.",
    "h": "",
    "o": 2,
    "l": "2"
  },
  {
    "id": "17008003",
    "b": 17,
    "c": 8,
    "v": 3,
    "t": "And the songs of the temple shall be howlings in that day,” says the Lord God. “The dead bodies shall be many. In every place one shall throw them out with silence.”",
    "h": "",
    "o": 3,
    "l": "3"
  },
  {
    "id": "17008004",
    "b": 17,
    "c": 8,
    "v": 4,
    "t": "Hear this, you who trample upon the needy, even to make the poor of the land to fail,",
    "h": "",
    "o": 4,
    "l": "4"
  },
  {
    "id": "17008005",
    "b": 17,
    "c": 8,
    "v": 5,
    "t": "Saying, “When will the new moon be gone so that we may sell grain? And the Sabbath, that we may set forth wheat, making the ephah small and the shekel great, and perverting the balances by deceit;",
    "h": "",
    "o": 5,
    "l": "5"
  },
  {
    "id": "17008006",
    "b": 17,
    "c": 8,
    "v": 6,
    "t": "That we may buy the poor for silver and the needy for a pair of sandals; and sell the chaff of the wheat?”",
    "h": "",
    "o": 6,
    "l": "6"
  },
  {
    "id": "17008007",
    "b": 17,
    "c": 8,
    "v": 7,
    "t": "The Lord has sworn by the Glory of Jacob, “Surely I will never forget any of their works.",
    "h": "",
    "o": 7,
    "l": "7"
  },
  {
    "id": "17008008",
    "b": 17,
    "c": 8,
    "v": 8,
    "t": "Shall not the land tremble for this, and all who dwell in it mourn? And all of it shall rise up like a flood. And it shall overflow and sink like the Nile of Egypt.",
    "h": "",
    "o": 8,
    "l": "8"
  },
  {
    "id": "17008009",
    "b": 17,
    "c": 8,
    "v": 9,
    "t": "And it shall be in that day,” says the Lord God, “I will cause the sun to go down at noon, and I will darken the earth in the light of day.",
    "h": "",
    "o": 9,
    "l": "9"
  },
  {
    "id": "17008010",
    "b": 17,
    "c": 8,
    "v": 10,
    "t": "And I will turn your feasts into mourning, and all your songs into weeping; and I will bring up sackcloth on all loins, and baldness on every head. And I will make it like the mourning of an only son, and the end of it like a bitter day.",
    "h": "",
    "o": 10,
    "l": "10"
  },
  {
    "id": "17008011",
    "b": 17,
    "c": 8,
    "v": 11,
    "t": "Behold, the days come,” says the Lord God, “that I will send a famine in the land; not a famine of bread nor a thirst for water, but of hearing the words of the Lord.",
    "h": "",
    "o": 11,
    "l": "11"
  },
  {
    "id": "17008012",
    "b": 17,
    "c": 8,
    "v": 12,
    "t": "And they shall wander from sea to sea, and from the north even to the east; they shall run to and fro to seek the Word of the Lord, and shall not find it.",
    "h": "",
    "o": 12,
    "l": "12"
  },
  {
    "id": "17008013",
    "b": 17,
    "c": 8,
    "v": 13,
    "t": "In that day the beautiful virgins and the young men shall faint for thirst.",
    "h": "",
    "o": 13,
    "l": "13"
  },
  {
    "id": "17008014",
    "b": 17,
    "c": 8,
    "v": 14,
    "t": "Those who swear by the sin of Samaria and say, ‘ As your God lives, O Dan,’ and, ‘ As the way of Beersheba lives’—even they shall fall and never rise up again.”",
    "h": "",
    "o": 14,
    "l": "14"
  },
  {
    "id": "17009001",
    "b": 17,
    "c": 9,
    "v": 1,
    "t": "I saw the Lord standing by the altar. And He said, “Strike the lintel of the door, so that the thresholds shall shake; and break them on the heads of all of them. And I will kill the last of them with the sword. Not one of them fleeing will get away, and not a fugitive of them will escape.",
    "h": "CHAPTER NINE",
    "o": 1,
    "l": "1"
  },
  {
    "id": "17009002",
    "b": 17,
    "c": 9,
    "v": 2,
    "t": "If they dig into the grave, there My hand shall take them. And if they go up to the heavens, I will bring them down from there.",
    "h": "",
    "o": 2,
    "l": "2"
  },
  {
    "id": "17009003",
    "b": 17,
    "c": 9,
    "v": 3,
    "t": "And if they hide themselves in the top of Carmel, I will search and take them out from there. And if they are hidden from My sight in the bottom of the sea, I will command the serpent there, and he shall bite them.",
    "h": "",
    "o": 3,
    "l": "3"
  },
  {
    "id": "17009004",
    "b": 17,
    "c": 9,
    "v": 4,
    "t": "And if they go into captivity before their enemies, I will command the sword there, and it shall kill them; and I will set My eyes upon them for evil, and not for good.”",
    "h": "",
    "o": 4,
    "l": "4"
  },
  {
    "id": "17009005",
    "b": 17,
    "c": 9,
    "v": 5,
    "t": "And the Lord God of hosts is He Who touches the land, and it shall melt, and all who dwell in it shall mourn. And all of it shall rise up like a flood, and sink down like the Nile of Egypt.",
    "h": "",
    "o": 5,
    "l": "5"
  },
  {
    "id": "17009006",
    "b": 17,
    "c": 9,
    "v": 6,
    "t": "It is He Who builds His staircase in the heavens, and He has founded the heavens over the earth; He Who calls for the waters of the sea, and pours them out upon the face of the earth; the Lord is His name.",
    "h": "",
    "o": 6,
    "l": "6"
  },
  {
    "id": "17009007",
    "b": 17,
    "c": 9,
    "v": 7,
    "t": "“Are you not like the children of the Ethiopians to Me, O children of Israel,” says the Lord ? “Have I not brought Israel up out of the land of Egypt—and the Philistines from Caphtor, and the Syrians from Kir?",
    "h": "",
    "o": 7,
    "l": "7"
  },
  {
    "id": "17009008",
    "b": 17,
    "c": 9,
    "v": 8,
    "t": "Behold, the eyes of the Lord God are on the sinful kingdom, and I will destroy it from the face of the earth; except that I will not completely destroy the house of Jacob,” says the Lord.",
    "h": "",
    "o": 8,
    "l": "8"
  },
  {
    "id": "17009009",
    "b": 17,
    "c": 9,
    "v": 9,
    "t": "“For lo, I will command, and I will shake the house of Israel among all the nations, as one shakes with a sieve, yet not a grain shall fall to the earth.",
    "h": "",
    "o": 9,
    "l": "9"
  },
  {
    "id": "17009010",
    "b": 17,
    "c": 9,
    "v": 10,
    "t": "All the sinners of My people shall die by the sword, who say, ‘The evil shall not draw near, or confront us.’",
    "h": "",
    "o": 10,
    "l": "10"
  },
  {
    "id": "17009011",
    "b": 17,
    "c": 9,
    "v": 11,
    "t": "In that day I will raise up the tabernacle of David that has fallen, and close up its breaches; and I will raise up its ruins, and I will build it as in the days of old;",
    "h": "",
    "o": 11,
    "l": "11"
  },
  {
    "id": "17009012",
    "b": 17,
    "c": 9,
    "v": 12,
    "t": "So that they may possess the remnant of Edom, and of all the nations on whom My name is called,” says the Lord who is doing this.",
    "h": "",
    "o": 12,
    "l": "12"
  },
  {
    "id": "17009013",
    "b": 17,
    "c": 9,
    "v": 13,
    "t": "“Behold, the days come,” says the Lord, “that the plowman shall overtake the reaper, and the treader of grapes him who sows seed. And the mountains will drop sweet wine, and all the hills will flow with it.",
    "h": "",
    "o": 13,
    "l": "13"
  },
  {
    "id": "17009014",
    "b": 17,
    "c": 9,
    "v": 14,
    "t": "And I will bring back the exiles of My people Israel, and they shall build the cities which are desolate, and they shall live in them. And they shall plant vineyards and drink their wine. They shall also make gardens and eat their fruit.",
    "h": "",
    "o": 14,
    "l": "14"
  },
  {
    "id": "17009015",
    "b": 17,
    "c": 9,
    "v": 15,
    "t": "And I will plant them in their land, and they shall no more be pulled up out of their land which I have given them,” says the Lord your God.",
    "h": "",
    "o": 15,
    "l": "15"
  }
]